{
    "0": {
        "link": "/wiki/Jacob_Bentz",
        "title": "Sophia Eberlein",
        "year": "1931",
        "state": "North Dakota",
        "county": "Wells County",
        "type": [
            "murder"
        ]
    },
    "1": {
        "link": "/wiki/George_Floyd_protests_in_North_Dakota",
        "title": "George Floyd protests in North Dakota",
        "year": "2020",
        "state": "North Dakota",
        "county": "Morton County",
        "type": [
            "murder",
            "shooting",
            "riot"
        ]
    },
    "2": {
        "link": "/wiki/List_of_people_executed_in_North_Dakota",
        "title": "List of people executed in North Dakota",
        "year": "",
        "state": "North Dakota",
        "county": "",
        "type": []
    },
    "3": {
        "link": "/wiki/Zip_to_Zap",
        "title": "Zip to Zap",
        "year": "1969",
        "state": "North Dakota",
        "county": "Mercer County",
        "type": [
            "riot"
        ]
    },
    "4": {
        "link": "/wiki/Lynching_of_Charles_Bannon",
        "title": "Lynching of Charles Bannon",
        "year": "1931",
        "state": "North Dakota",
        "county": "Morton County",
        "type": [
            "murder",
            "robbery",
            "shooting"
        ]
    },
    "5": {
        "link": "/wiki/Dru_Sjodin",
        "title": "Murder of Dru Sjodin",
        "year": "2003",
        "state": "North Dakota",
        "county": "Grand Forks County",
        "type": [
            "murder",
            "kidnapping",
            "assault",
            "sexual assault"
        ]
    },
    "6": {
        "link": "/wiki/Sophia_Eberlein",
        "title": "Sophia Eberlein",
        "year": "1931",
        "state": "North Dakota",
        "county": "Wells County",
        "type": [
            "murder"
        ]
    },
    "7": {
        "link": "/wiki/Charles_Thurber",
        "title": "Charles Thurber",
        "year": "2020",
        "state": "North Dakota",
        "county": "Grand Forks County",
        "type": [
            "murder",
            "sexual assault"
        ]
    },
    "8": {
        "link": "/wiki/Matthew_Mechtel",
        "title": "2006 United States House of Representatives election in North Dakota",
        "year": "2006",
        "state": "North Dakota",
        "county": "Bowman County",
        "type": []
    },
    "9": {
        "link": "/wiki/John_Rooney_(murderer)",
        "title": "John Rooney (murderer)",
        "year": "1902",
        "state": "North Dakota",
        "county": "Cass County",
        "type": [
            "murder",
            "robbery"
        ]
    },
    "10": {
        "link": "/wiki/Murder_of_Amanda_Froistad",
        "title": "Murder of Amanda Froistad",
        "year": "1995",
        "state": "North Dakota",
        "county": "",
        "type": [
            "murder",
            "arson"
        ]
    },
    "11": {
        "link": "/wiki/Capital_punishment_in_North_Dakota",
        "title": "Capital punishment in North Dakota",
        "year": "1915",
        "state": "North Dakota",
        "county": "Cass County",
        "type": [
            "murder",
            "robbery",
            "kidnapping"
        ]
    }
}