{
    "0": {
        "link": "/wiki/Indigenous_Peoples_Day_of_Rage",
        "title": "Indigenous Peoples Day of Rage",
        "year": "2020",
        "state": "Oregon",
        "county": "Multnomah County",
        "type": [
            "shooting",
            "murder",
            "arson",
            "robbery",
            "riot"
        ]
    },
    "1": {
        "link": "/wiki/Richard_Laurence_Marquette",
        "title": "Richard Laurence Marquette",
        "year": "1961",
        "state": "Oregon",
        "county": "Multnomah County",
        "type": [
            "murder",
            "sexual assault"
        ]
    },
    "2": {
        "link": "/wiki/Killings_of_Aaron_Danielson_and_Michael_Reinoehl",
        "title": "Killings of Aaron Danielson and Michael Reinoehl",
        "year": "2020",
        "state": "Oregon",
        "county": "Marion County",
        "type": [
            "murder",
            "shooting",
            "riot"
        ]
    },
    "3": {
        "link": "/wiki/Murder_of_Daniel_Brophy",
        "title": "Murder of Daniel Brophy",
        "year": "2018",
        "state": "Oregon",
        "county": "Multnomah County",
        "type": [
            "murder"
        ]
    },
    "4": {
        "link": "/wiki/Murder_of_Yolanda_Panek",
        "title": "Murder of Yolanda Panek",
        "year": "1995",
        "state": "Oregon",
        "county": "Umatilla County",
        "type": [
            "murder",
            "kidnapping"
        ]
    },
    "5": {
        "link": "/wiki/Ralph_Wilcox",
        "title": "Ralph Wilcox",
        "year": "1877",
        "state": "Oregon",
        "county": "Multnomah County",
        "type": [
            "murder",
            "shooting"
        ]
    },
    "6": {
        "link": "/wiki/Crime_in_Oregon",
        "title": "Crime in Oregon",
        "year": "",
        "state": "Oregon",
        "county": "Marion County",
        "type": [
            "murder"
        ]
    },
    "7": {
        "link": "/wiki/Normandale_Park_shooting",
        "title": "Normandale Park shooting",
        "year": "2022",
        "state": "Oregon",
        "county": "Multnomah County",
        "type": [
            "murder",
            "mass murder",
            "shooting"
        ]
    },
    "8": {
        "link": "/wiki/Cowden_family_murders",
        "title": "Cowden family murders",
        "year": "1974",
        "state": "Oregon",
        "county": "Jackson County",
        "type": [
            "murder",
            "mass murder",
            "shooting",
            "kidnapping"
        ]
    },
    "9": {
        "link": "/wiki/Murder_of_Thelma_Taylor",
        "title": "Murder of Thelma Taylor",
        "year": "1949",
        "state": "Oregon",
        "county": "Multnomah County",
        "type": [
            "murder",
            "robbery",
            "kidnapping",
            "sexual assault"
        ]
    },
    "10": {
        "link": "/wiki/Bend,_Oregon_shooting",
        "title": "Bend, Oregon shooting",
        "year": "2022",
        "state": "Oregon",
        "county": "Deschutes County",
        "type": [
            "murder",
            "mass murder",
            "shooting"
        ]
    },
    "11": {
        "link": "/wiki/Oregon_State_Penitentiary",
        "title": "Oregon State Penitentiary",
        "year": "1925",
        "state": "Oregon",
        "county": "Marion County",
        "type": [
            "murder",
            "riot"
        ]
    },
    "12": {
        "link": "/wiki/Kip_Kinkel",
        "title": "Thurston High School shooting",
        "year": "1998",
        "state": "Oregon",
        "county": "Lane County",
        "type": [
            "murder",
            "mass murder",
            "shooting",
            "robbery"
        ]
    },
    "13": {
        "link": "/wiki/Edward_Delon_Warren",
        "title": "Edward Delon Warren",
        "year": "2003",
        "state": "Oregon",
        "county": "Marion County",
        "type": [
            "murder",
            "robbery",
            "shooting",
            "assault"
        ]
    },
    "14": {
        "link": "/wiki/Umpqua_Community_College_shooting",
        "title": "Umpqua Community College shooting",
        "year": "2015",
        "state": "Oregon",
        "county": "Douglas County",
        "type": [
            "murder",
            "mass murder",
            "shooting"
        ]
    },
    "15": {
        "link": "/wiki/Thurston_High_School_shooting",
        "title": "Thurston High School shooting",
        "year": "1998",
        "state": "Oregon",
        "county": "Lane County",
        "type": [
            "murder",
            "mass murder",
            "shooting",
            "robbery"
        ]
    },
    "16": {
        "link": "/wiki/Thomas_Eugene_Creech",
        "title": "Thomas Eugene Creech",
        "year": "1974",
        "state": "Oregon",
        "county": "Grant County",
        "type": [
            "murder",
            "robbery",
            "sexual assault"
        ]
    },
    "17": {
        "link": "/wiki/Brooke_Wilberger",
        "title": "Murder of Brooke Wilberger",
        "year": "2004",
        "state": "Oregon",
        "county": "Benton County",
        "type": [
            "murder",
            "robbery",
            "kidnapping",
            "sexual assault"
        ]
    },
    "18": {
        "link": "/wiki/Jake_Gardner",
        "title": "Killing of James Scurlock",
        "year": "2020",
        "state": "Oregon",
        "county": "Crook County",
        "type": [
            "murder",
            "shooting",
            "sexual assault"
        ]
    },
    "19": {
        "link": "/wiki/Black_Lives_Matter_art_in_Portland,_Oregon",
        "title": "Black Lives Matter art in Portland, Oregon",
        "year": "",
        "state": "Oregon",
        "county": "Multnomah County",
        "type": [
            "murder"
        ]
    },
    "20": {
        "link": "/wiki/Janet_M._Smith",
        "title": "Gresham cat hostage taking incident",
        "year": "1994",
        "state": "Oregon",
        "county": "Multnomah County",
        "type": [
            "murder",
            "shooting"
        ]
    },
    "21": {
        "link": "/wiki/Christian_Longo",
        "title": "Christian Longo",
        "year": "",
        "state": "Oregon",
        "county": "Lincoln County",
        "type": [
            "murder",
            "mass murder"
        ]
    },
    "22": {
        "link": "/wiki/Paul_Zahniser",
        "title": "Paul Zahniser",
        "year": "1964",
        "state": "Oregon",
        "county": "Klamath County",
        "type": [
            "murder"
        ]
    },
    "23": {
        "link": "/wiki/Wall_of_Moms",
        "title": "Wall of Moms",
        "year": "",
        "state": "Oregon",
        "county": "Multnomah County",
        "type": [
            "kidnapping"
        ]
    },
    "24": {
        "link": "/wiki/Albina_Riot_of_1967",
        "title": "Albina Riot of 1967",
        "year": "1967",
        "state": "Oregon",
        "county": "Multnomah County",
        "type": [
            "robbery",
            "riot"
        ]
    },
    "25": {
        "link": "/wiki/LaVoy_Finicum",
        "title": "LaVoy Finicum",
        "year": "2016",
        "state": "Oregon",
        "county": "Harney County",
        "type": [
            "murder",
            "shooting"
        ]
    },
    "26": {
        "link": "/wiki/Robert_Folkes",
        "title": "Robert Folkes",
        "year": "1945",
        "state": "Oregon",
        "county": "Multnomah County",
        "type": [
            "murder",
            "sexual assault"
        ]
    },
    "27": {
        "link": "/wiki/Coffee_Creek_Correctional_Facility",
        "title": "Coffee Creek Correctional Facility",
        "year": "",
        "state": "Oregon",
        "county": "Clackamas County",
        "type": [
            "murder"
        ]
    },
    "28": {
        "link": "/wiki/Gresham_cat_hostage_taking_incident",
        "title": "Gresham cat hostage taking incident",
        "year": "1994",
        "state": "Oregon",
        "county": "Multnomah County",
        "type": [
            "murder",
            "shooting"
        ]
    },
    "29": {
        "link": "/wiki/Lyle_Bigbee",
        "title": "Lyle Bigbee",
        "year": "1942",
        "state": "Oregon",
        "county": "Linn County",
        "type": [
            "murder",
            "arson"
        ]
    },
    "30": {
        "link": "/wiki/Buzz_Holmstrom",
        "title": "Buzz Holmstrom",
        "year": "1946",
        "state": "Oregon",
        "county": "Coos County",
        "type": [
            "murder",
            "shooting"
        ]
    },
    "31": {
        "link": "/wiki/Randall_Woodfield",
        "title": "Randall Woodfield",
        "year": "1980",
        "state": "Oregon",
        "county": "Lane County",
        "type": [
            "murder",
            "robbery",
            "assault",
            "kidnapping"
        ]
    },
    "32": {
        "link": "/wiki/Jim_Bradley_(basketball)",
        "title": "Jim Bradley (basketball)",
        "year": "1982",
        "state": "Oregon",
        "county": "Multnomah County",
        "type": [
            "murder"
        ]
    },
    "33": {
        "link": "/wiki/George_Floyd_protests_in_Portland,_Oregon",
        "title": "George Floyd protests in Portland, Oregon",
        "year": "2020",
        "state": "Oregon",
        "county": "Multnomah County",
        "type": [
            "shooting",
            "murder",
            "arson",
            "robbery",
            "riot"
        ]
    },
    "34": {
        "link": "/wiki/Murders_of_Ashley_Pond_and_Miranda_Gaddis",
        "title": "Ward Weaver III",
        "year": "1984",
        "state": "Oregon",
        "county": "Clackamas County",
        "type": [
            "murder",
            "kidnapping",
            "assault",
            "sexual assault"
        ]
    },
    "35": {
        "link": "/wiki/Jacob_Tyler_Roberts",
        "title": "Clackamas Town Center shooting",
        "year": "2012",
        "state": "Oregon",
        "county": "Clackamas County",
        "type": [
            "murder",
            "robbery",
            "shooting",
            "sexual assault"
        ]
    },
    "36": {
        "link": "/wiki/Demetria_Hester",
        "title": "Demetria Hester",
        "year": "2017",
        "state": "Oregon",
        "county": "Multnomah County",
        "type": [
            "murder",
            "shooting",
            "assault"
        ]
    },
    "37": {
        "link": "/wiki/Rosemary_Anderson_High_School_shooting",
        "title": "Rosemary Anderson High School",
        "year": "1983",
        "state": "Oregon",
        "county": "Multnomah County",
        "type": [
            "shooting"
        ]
    },
    "38": {
        "link": "/wiki/Murder_of_Mulugeta_Seraw",
        "title": "Murder of Mulugeta Seraw",
        "year": "1988",
        "state": "Oregon",
        "county": "Multnomah County",
        "type": [
            "murder",
            "assault",
            "riot"
        ]
    },
    "39": {
        "link": "/wiki/Chris_Harper-Mercer",
        "title": "Umpqua Community College shooting",
        "year": "2015",
        "state": "Oregon",
        "county": "Douglas County",
        "type": [
            "murder",
            "mass murder",
            "shooting"
        ]
    },
    "40": {
        "link": "/wiki/Lava_Lake_murders",
        "title": "Lava Lake murders",
        "year": "1924",
        "state": "Oregon",
        "county": "Deschutes County",
        "type": [
            "murder",
            "shooting"
        ]
    },
    "41": {
        "link": "/wiki/Aaron_Danielson",
        "title": "Killings of Aaron Danielson and Michael Reinoehl",
        "year": "2020",
        "state": "Oregon",
        "county": "Marion County",
        "type": [
            "murder",
            "shooting",
            "riot"
        ]
    },
    "42": {
        "link": "/wiki/Reynolds_High_School_shooting",
        "title": "Reynolds High School (Oregon)",
        "year": "2014",
        "state": "Oregon",
        "county": "Multnomah County",
        "type": [
            "murder",
            "shooting"
        ]
    },
    "43": {
        "link": "/wiki/Stanley_Bernson",
        "title": "Stanley Bernson",
        "year": "1978",
        "state": "Oregon",
        "county": "Curry County",
        "type": [
            "kidnapping",
            "sexual assault",
            "murder",
            "hijacking",
            "assault"
        ]
    },
    "44": {
        "link": "/wiki/William_Dennison_Clark",
        "title": "William Dennison Clark",
        "year": "",
        "state": "Oregon",
        "county": "Marion County",
        "type": [
            "murder",
            "shooting"
        ]
    },
    "45": {
        "link": "/wiki/1984_Rajneeshee_bioterror_attack",
        "title": "1984 Rajneeshee bioterror attack",
        "year": "1984",
        "state": "Oregon",
        "county": "Wasco County",
        "type": [
            "murder",
            "terrorism"
        ]
    },
    "46": {
        "link": "/wiki/Ardenwald_axe_murders",
        "title": "Ardenwald axe murders",
        "year": "1911",
        "state": "Oregon",
        "county": "Clackamas County",
        "type": [
            "murder",
            "mass murder",
            "robbery",
            "assault"
        ]
    },
    "47": {
        "link": "/wiki/Harry_Minto",
        "title": "Harry Minto",
        "year": "1915",
        "state": "Oregon",
        "county": "Linn County",
        "type": [
            "murder"
        ]
    },
    "48": {
        "link": "/wiki/Murder_of_Brooke_Wilberger",
        "title": "Murder of Brooke Wilberger",
        "year": "2004",
        "state": "Oregon",
        "county": "Benton County",
        "type": [
            "murder",
            "robbery",
            "kidnapping",
            "sexual assault"
        ]
    },
    "49": {
        "link": "/wiki/Abuse_of_Kylie_Freeman",
        "title": "Abuse of Kylie Freeman",
        "year": "",
        "state": "Oregon",
        "county": "Grant County",
        "type": [
            "assault",
            "sexual assault"
        ]
    },
    "50": {
        "link": "/wiki/Nightmare_Elk",
        "title": "Nightmare Elk",
        "year": "",
        "state": "Oregon",
        "county": "Multnomah County",
        "type": [
            "riot"
        ]
    },
    "51": {
        "link": "/wiki/Murder_of_Martha_Morrison",
        "title": "Murder of Martha Morrison",
        "year": "1974",
        "state": "Oregon",
        "county": "Multnomah County",
        "type": [
            "murder",
            "kidnapping"
        ]
    },
    "52": {
        "link": "/wiki/John_Fautenberry",
        "title": "John Fautenberry",
        "year": "2009",
        "state": "Oregon",
        "county": "Washington County",
        "type": [
            "murder",
            "robbery",
            "kidnapping"
        ]
    },
    "53": {
        "link": "/wiki/Shooting_of_Kendra_James",
        "title": "Shooting of Kendra James",
        "year": "2003",
        "state": "Oregon",
        "county": "Multnomah County",
        "type": [
            "murder",
            "shooting"
        ]
    },
    "54": {
        "link": "/wiki/Michael_Francke",
        "title": "Michael Francke",
        "year": "1989",
        "state": "Oregon",
        "county": "Marion County",
        "type": [
            "murder"
        ]
    },
    "55": {
        "link": "/wiki/George_LeBreton",
        "title": "George LeBreton",
        "year": "1844",
        "state": "Oregon",
        "county": "Multnomah County",
        "type": [
            "murder"
        ]
    },
    "56": {
        "link": "/wiki/Bobby_Jack_Fowler",
        "title": "Bobby Jack Fowler",
        "year": "2006",
        "state": "Oregon",
        "county": "Marion County",
        "type": [
            "kidnapping",
            "sexual assault",
            "murder",
            "shooting",
            "assault"
        ]
    },
    "57": {
        "link": "/wiki/Shane_Patrick_Moore",
        "title": "Tucker Reed",
        "year": "2020",
        "state": "Oregon",
        "county": "Jackson County",
        "type": [
            "murder",
            "shooting",
            "sexual assault"
        ]
    },
    "58": {
        "link": "/wiki/Murders_of_Larry_Peyton_and_Beverly_Allan",
        "title": "Murders of Larry Peyton and Beverly Allan",
        "year": "1960",
        "state": "Oregon",
        "county": "Multnomah County",
        "type": [
            "murder",
            "kidnapping",
            "assault",
            "sexual assault"
        ]
    },
    "59": {
        "link": "/wiki/Clackamas_Town_Center_shooting",
        "title": "Clackamas Town Center shooting",
        "year": "2012",
        "state": "Oregon",
        "county": "Clackamas County",
        "type": [
            "murder",
            "robbery",
            "shooting",
            "sexual assault"
        ]
    },
    "60": {
        "link": "/wiki/John_K._Giles",
        "title": "John K. Giles",
        "year": "1979",
        "state": "Oregon",
        "county": "Multnomah County",
        "type": [
            "murder",
            "robbery"
        ]
    },
    "61": {
        "link": "/wiki/Roxanne_Ellis",
        "title": "Murder of Roxanne Ellis and Michelle Abdill",
        "year": "",
        "state": "Oregon",
        "county": "Jackson County",
        "type": [
            "murder",
            "sexual assault"
        ]
    },
    "62": {
        "link": "/wiki/Leroy_McGahuey",
        "title": "Leroy McGahuey",
        "year": "1962",
        "state": "Oregon",
        "county": "Marion County",
        "type": [
            "murder",
            "shooting"
        ]
    },
    "63": {
        "link": "/wiki/Michelle_Abdill",
        "title": "Murder of Roxanne Ellis and Michelle Abdill",
        "year": "",
        "state": "Oregon",
        "county": "Jackson County",
        "type": [
            "murder",
            "sexual assault"
        ]
    },
    "64": {
        "link": "/wiki/2016_Portland,_Oregon_riots",
        "title": "2016 Portland, Oregon riots",
        "year": "2016",
        "state": "Oregon",
        "county": "Multnomah County",
        "type": [
            "murder",
            "shooting",
            "assault",
            "riot"
        ]
    },
    "65": {
        "link": "/wiki/Jeremy_Joseph_Christian",
        "title": "2017 Portland train attack",
        "year": "2017",
        "state": "Oregon",
        "county": "Multnomah County",
        "type": [
            "murder",
            "mass murder",
            "assault",
            "riot"
        ]
    },
    "66": {
        "link": "/wiki/Chauncey_Bishop",
        "title": "Chauncey Bishop",
        "year": "1927",
        "state": "Oregon",
        "county": "Umatilla County",
        "type": [
            "murder"
        ]
    },
    "67": {
        "link": "/wiki/Jerry_Brudos",
        "title": "Jerry Brudos",
        "year": "2006",
        "state": "Oregon",
        "county": "Marion County",
        "type": [
            "murder",
            "robbery"
        ]
    },
    "68": {
        "link": "/wiki/Pacific_Northwest_Youth_Liberation_Front",
        "title": "George Floyd protests in Portland, Oregon",
        "year": "2020",
        "state": "Oregon",
        "county": "Multnomah County",
        "type": [
            "shooting",
            "murder",
            "arson",
            "robbery",
            "riot"
        ]
    },
    "69": {
        "link": "/wiki/Cheryl_Keeton",
        "title": "Cheryl Keeton",
        "year": "1986",
        "state": "Oregon",
        "county": "Multnomah County",
        "type": [
            "murder"
        ]
    },
    "70": {
        "link": "/wiki/Susan_Monica",
        "title": "Susan Monica",
        "year": "2015",
        "state": "Oregon",
        "county": "Jackson County",
        "type": [
            "murder",
            "robbery",
            "kidnapping"
        ]
    },
    "71": {
        "link": "/wiki/David_Durham_(fugitive)",
        "title": "David Durham (fugitive)",
        "year": "1967",
        "state": "Oregon",
        "county": "Lincoln County",
        "type": [
            "murder",
            "shooting",
            "kidnapping"
        ]
    },
    "72": {
        "link": "/wiki/1985_Rajneeshee_assassination_plot",
        "title": "1985 Rajneeshee assassination plot",
        "year": "1985",
        "state": "Oregon",
        "county": "Multnomah County",
        "type": [
            "murder",
            "terrorism"
        ]
    },
    "73": {
        "link": "/wiki/Rose_City_Justice",
        "title": "George Floyd protests in Portland, Oregon",
        "year": "2020",
        "state": "Oregon",
        "county": "Multnomah County",
        "type": [
            "shooting",
            "murder",
            "arson",
            "robbery",
            "riot"
        ]
    },
    "74": {
        "link": "/wiki/Leathers_Oil_Company_murders",
        "title": "Leathers Oil Company murders",
        "year": "1994",
        "state": "Oregon",
        "county": "Multnomah County",
        "type": [
            "kidnapping",
            "murder",
            "mass murder",
            "robbery",
            "shooting"
        ]
    },
    "75": {
        "link": "/wiki/Christopher_Brathwaite",
        "title": "Christopher Brathwaite",
        "year": "1984",
        "state": "Oregon",
        "county": "Coos County",
        "type": [
            "murder",
            "shooting"
        ]
    },
    "76": {
        "link": "/wiki/George_Floyd_protests_in_Oregon",
        "title": "George Floyd protests in Oregon",
        "year": "2020",
        "state": "Oregon",
        "county": "Linn County",
        "type": [
            "riot"
        ]
    },
    "77": {
        "link": "/wiki/Leland_v._Oregon",
        "title": "Leland v. Oregon",
        "year": "",
        "state": "Oregon",
        "county": "Josephine County",
        "type": [
            "murder",
            "robbery"
        ]
    },
    "78": {
        "link": "/wiki/Oak_Grove_Jane_Doe",
        "title": "Oak Grove Jane Doe",
        "year": "2004",
        "state": "Oregon",
        "county": "Clackamas County",
        "type": [
            "murder",
            "assault"
        ]
    },
    "79": {
        "link": "/wiki/Cesar_Barone",
        "title": "Cesar Barone",
        "year": "2009",
        "state": "Oregon",
        "county": "Marion County",
        "type": [
            "murder",
            "shooting",
            "assault",
            "sexual assault"
        ]
    },
    "80": {
        "link": "/wiki/Oregon_v._Guzek",
        "title": "Oregon v. Guzek",
        "year": "",
        "state": "Oregon",
        "county": "Clatsop County",
        "type": [
            "murder"
        ]
    },
    "81": {
        "link": "/wiki/Killing_of_Alonzo_Tucker",
        "title": "Killing of Alonzo Tucker",
        "year": "1902",
        "state": "Oregon",
        "county": "Clackamas County",
        "type": [
            "murder",
            "shooting",
            "assault",
            "sexual assault"
        ]
    },
    "82": {
        "link": "/wiki/Sebastian_Shaw_(serial_killer)",
        "title": "Sebastian Shaw (serial killer)",
        "year": "2021",
        "state": "Oregon",
        "county": "Marion County",
        "type": [
            "murder",
            "robbery",
            "assault",
            "sexual assault"
        ]
    },
    "83": {
        "link": "/wiki/Murder_of_Larnell_Bruce",
        "title": "Murder of Larnell Bruce",
        "year": "2016",
        "state": "Oregon",
        "county": "Multnomah County",
        "type": [
            "murder"
        ]
    },
    "84": {
        "link": "/wiki/Oregon_Museum_Tavern_shooting",
        "title": "Oregon Museum Tavern shooting",
        "year": "1981",
        "state": "Oregon",
        "county": "Marion County",
        "type": [
            "murder",
            "mass murder",
            "shooting"
        ]
    },
    "85": {
        "link": "/wiki/Tiloukaikt",
        "title": "Tiloukaikt",
        "year": "1835",
        "state": "Oregon",
        "county": "Umatilla County",
        "type": [
            "murder",
            "mass murder"
        ]
    },
    "86": {
        "link": "/wiki/Homer_Jackson",
        "title": "Homer Jackson",
        "year": "1983",
        "state": "Oregon",
        "county": "Multnomah County",
        "type": [
            "murder",
            "robbery",
            "shooting",
            "assault"
        ]
    },
    "87": {
        "link": "/wiki/Andrew_David_Edwards",
        "title": "Andrew David Edwards",
        "year": "1987",
        "state": "Oregon",
        "county": "Coos County",
        "type": [
            "murder"
        ]
    },
    "88": {
        "link": "/wiki/John_Arthur_Ackroyd",
        "title": "John Arthur Ackroyd",
        "year": "2016",
        "state": "Oregon",
        "county": "Marion County",
        "type": [
            "murder",
            "robbery",
            "kidnapping",
            "sexual assault"
        ]
    },
    "89": {
        "link": "/wiki/Woodburn_bank_bombing",
        "title": "Woodburn bank bombing",
        "year": "2008",
        "state": "Oregon",
        "county": "Marion County",
        "type": [
            "murder",
            "robbery"
        ]
    },
    "90": {
        "link": "/wiki/Cline_Falls_axe_attack",
        "title": "Cline Falls axe attack",
        "year": "1977",
        "state": "Oregon",
        "county": "Deschutes County",
        "type": [
            "murder"
        ]
    },
    "91": {
        "link": "/wiki/Kirk_Reeves",
        "title": "Kirk Reeves",
        "year": "2012",
        "state": "Oregon",
        "county": "Multnomah County",
        "type": [
            "shooting"
        ]
    },
    "92": {
        "link": "/wiki/Diane_Downs",
        "title": "Diane Downs",
        "year": "1983",
        "state": "Oregon",
        "county": "Lane County",
        "type": [
            "murder",
            "shooting",
            "assault"
        ]
    },
    "93": {
        "link": "/wiki/Martha_Morrison",
        "title": "Murder of Martha Morrison",
        "year": "1974",
        "state": "Oregon",
        "county": "Multnomah County",
        "type": [
            "murder",
            "kidnapping"
        ]
    },
    "94": {
        "link": "/wiki/Joshua_Marquis",
        "title": "Joshua Marquis",
        "year": "1987",
        "state": "Oregon",
        "county": "Clatsop County",
        "type": [
            "murder"
        ]
    },
    "95": {
        "link": "/wiki/Jared_Michael_Padgett",
        "title": "Reynolds High School (Oregon)",
        "year": "2014",
        "state": "Oregon",
        "county": "Multnomah County",
        "type": [
            "murder",
            "shooting"
        ]
    },
    "96": {
        "link": "/wiki/W.O.W._Hall_shooting",
        "title": "W.O.W. Hall",
        "year": "2022",
        "state": "Oregon",
        "county": "Lane County",
        "type": [
            "mass murder",
            "shooting"
        ]
    },
    "97": {
        "link": "/wiki/Kintpuash",
        "title": "Kintpuash",
        "year": "1873",
        "state": "Oregon",
        "county": "Klamath County",
        "type": [
            "murder",
            "robbery"
        ]
    },
    "98": {
        "link": "/wiki/Ward_Weaver_III",
        "title": "Ward Weaver III",
        "year": "1984",
        "state": "Oregon",
        "county": "Clackamas County",
        "type": [
            "murder",
            "kidnapping",
            "assault",
            "sexual assault"
        ]
    },
    "99": {
        "link": "/wiki/Cornelius_Gilliam",
        "title": "Cornelius Gilliam",
        "year": "1848",
        "state": "Oregon",
        "county": "Multnomah County",
        "type": [
            "murder",
            "mass murder"
        ]
    },
    "100": {
        "link": "/wiki/William_Scott_Smith",
        "title": "William Scott Smith",
        "year": "1981",
        "state": "Oregon",
        "county": "Marion County",
        "type": [
            "kidnapping",
            "shooting",
            "murder",
            "robbery",
            "assault"
        ]
    },
    "101": {
        "link": "/wiki/Marion_Eugene_Carl",
        "title": "Marion Eugene Carl",
        "year": "1998",
        "state": "Oregon",
        "county": "Douglas County",
        "type": [
            "murder"
        ]
    },
    "102": {
        "link": "/wiki/Jim_Elkins_(criminal)",
        "title": "Jim Elkins (criminal)",
        "year": "",
        "state": "Oregon",
        "county": "Multnomah County",
        "type": [
            "murder",
            "shooting"
        ]
    },
    "103": {
        "link": "/wiki/Jeannace_June_Freeman",
        "title": "Jeannace June Freeman",
        "year": "1961",
        "state": "Oregon",
        "county": "",
        "type": [
            "murder",
            "assault"
        ]
    },
    "104": {
        "link": "/wiki/Nancy_Crampton_Brophy",
        "title": "Murder of Daniel Brophy",
        "year": "2018",
        "state": "Oregon",
        "county": "Multnomah County",
        "type": [
            "murder"
        ]
    },
    "105": {
        "link": "/wiki/Robert_Wayne_Danielson",
        "title": "Robert Wayne Danielson",
        "year": "1995",
        "state": "Oregon",
        "county": "Lane County",
        "type": [
            "murder",
            "robbery",
            "kidnapping"
        ]
    },
    "106": {
        "link": "/wiki/Felony_murder_rule_in_Oregon",
        "title": "Felony murder rule in Oregon",
        "year": "",
        "state": "Oregon",
        "county": "",
        "type": [
            "murder"
        ]
    },
    "107": {
        "link": "/wiki/Oregon_State_Capitol_breach",
        "title": "Oregon State Capitol breach",
        "year": "2020",
        "state": "Oregon",
        "county": "Marion County",
        "type": [
            "assault",
            "riot"
        ]
    },
    "108": {
        "link": "/wiki/Mike_Current",
        "title": "Mike Current",
        "year": "2012",
        "state": "Oregon",
        "county": "Washington County",
        "type": [
            "murder",
            "shooting",
            "assault",
            "sexual assault"
        ]
    },
    "109": {
        "link": "/wiki/Todd_Alan_Reed",
        "title": "Todd Alan Reed",
        "year": "1999",
        "state": "Oregon",
        "county": "Multnomah County",
        "type": [
            "kidnapping",
            "sexual assault",
            "murder",
            "robbery",
            "assault"
        ]
    },
    "110": {
        "link": "/wiki/Scott_William_Cox",
        "title": "Scott William Cox",
        "year": "1991",
        "state": "Oregon",
        "county": "Multnomah County",
        "type": [
            "murder",
            "robbery",
            "assault",
            "sexual assault"
        ]
    },
    "111": {
        "link": "/wiki/Thelma_Taylor",
        "title": "Murder of Thelma Taylor",
        "year": "1949",
        "state": "Oregon",
        "county": "Multnomah County",
        "type": [
            "murder",
            "robbery",
            "kidnapping",
            "sexual assault"
        ]
    },
    "112": {
        "link": "/wiki/Red_House_eviction_defense",
        "title": "Red House eviction defense",
        "year": "2020",
        "state": "Oregon",
        "county": "Multnomah County",
        "type": [
            "murder"
        ]
    },
    "113": {
        "link": "/wiki/Dayton_Leroy_Rogers",
        "title": "Dayton Leroy Rogers",
        "year": "1988",
        "state": "Oregon",
        "county": "Clackamas County",
        "type": [
            "murder"
        ]
    },
    "114": {
        "link": "/wiki/Jon_Paul_Steuer",
        "title": "Jon Paul Steuer",
        "year": "2018",
        "state": "Oregon",
        "county": "Multnomah County",
        "type": [
            "murder"
        ]
    },
    "115": {
        "link": "/wiki/Capital_punishment_in_Oregon",
        "title": "Capital punishment in Oregon",
        "year": "",
        "state": "Oregon",
        "county": "Marion County",
        "type": [
            "murder"
        ]
    },
    "116": {
        "link": "/wiki/2017_Portland_train_attack",
        "title": "2017 Portland train attack",
        "year": "2017",
        "state": "Oregon",
        "county": "Multnomah County",
        "type": [
            "murder",
            "mass murder",
            "assault",
            "riot"
        ]
    },
    "117": {
        "link": "/wiki/Harry_Charles_Moore",
        "title": "Harry Charles Moore",
        "year": "1992",
        "state": "Oregon",
        "county": "Marion County",
        "type": [
            "murder"
        ]
    },
    "118": {
        "link": "/wiki/Keith_Hunter_Jesperson",
        "title": "Keith Hunter Jesperson",
        "year": "",
        "state": "Oregon",
        "county": "Deschutes County",
        "type": [
            "murder",
            "assault",
            "sexual assault"
        ]
    },
    "119": {
        "link": "/wiki/Murder_of_Roxanne_Ellis_and_Michelle_Abdill",
        "title": "Murder of Roxanne Ellis and Michelle Abdill",
        "year": "",
        "state": "Oregon",
        "county": "Jackson County",
        "type": [
            "murder",
            "sexual assault"
        ]
    },
    "120": {
        "link": "/wiki/Douglas_Franklin_Wright",
        "title": "Douglas Franklin Wright",
        "year": "1996",
        "state": "Oregon",
        "county": "Marion County",
        "type": [
            "murder",
            "robbery",
            "shooting",
            "assault"
        ]
    },
    "121": {
        "link": "/wiki/Norm_Winningstad",
        "title": "Norm Winningstad",
        "year": "2010",
        "state": "Oregon",
        "county": "Lincoln County",
        "type": [
            "murder",
            "shooting"
        ]
    },
    "122": {
        "link": "/wiki/2020_deployment_of_federal_forces_in_the_United_States",
        "title": "2020 deployment of federal forces in the United States",
        "year": "2020",
        "state": "Oregon",
        "county": "Malheur County",
        "type": [
            "murder",
            "arson",
            "riot"
        ]
    },
    "123": {
        "link": "/wiki/William_Perry_Jackson",
        "title": "William Perry Jackson",
        "year": "1980",
        "state": "Oregon",
        "county": "Multnomah County",
        "type": [
            "murder",
            "robbery",
            "kidnapping",
            "sexual assault"
        ]
    },
    "124": {
        "link": "/wiki/Killing_of_Robert_Delgado",
        "title": "Killing of Robert Delgado",
        "year": "2021",
        "state": "Oregon",
        "county": "Multnomah County",
        "type": [
            "murder",
            "shooting"
        ]
    },
    "125": {
        "link": "/wiki/Hells_Canyon_Massacre",
        "title": "Hells Canyon Massacre",
        "year": "1887",
        "state": "Oregon",
        "county": "Wallowa County",
        "type": [
            "terrorism",
            "murder",
            "mass murder",
            "robbery"
        ]
    },
    "126": {
        "link": "/wiki/Earle_Nelson",
        "title": "Earle Nelson",
        "year": "1928",
        "state": "Oregon",
        "county": "Lake County",
        "type": [
            "murder",
            "sexual assault"
        ]
    },
    "127": {
        "link": "/wiki/Parents_of_Murdered_Children_Memorial",
        "title": "Parents of Murdered Children Memorial",
        "year": "",
        "state": "Oregon",
        "county": "Clackamas County",
        "type": [
            "murder"
        ]
    },
    "128": {
        "link": "/wiki/Omar_August_Pinson",
        "title": "Omar August Pinson",
        "year": "1997",
        "state": "Oregon",
        "county": "Polk County",
        "type": [
            "murder",
            "robbery",
            "shooting"
        ]
    },
    "129": {
        "link": "/wiki/Peter_French",
        "title": "Peter French",
        "year": "1897",
        "state": "Oregon",
        "county": "Deschutes County",
        "type": [
            "murder",
            "shooting"
        ]
    }
}